setup.py
django_forceadminlanguage.egg-info/PKG-INFO
django_forceadminlanguage.egg-info/SOURCES.txt
django_forceadminlanguage.egg-info/dependency_links.txt
django_forceadminlanguage.egg-info/not-zip-safe
django_forceadminlanguage.egg-info/top_level.txt
forceadminlanguage/__init__.py
forceadminlanguage/middleware.py