Metadata-Version: 1.1
Name: django-forceadminlanguage
Version: 0.0.1
Summary: Force Django Admin to show in one selected language.
Home-page: https://github.com/Brick85/django_forceadminlanguage/
Author: Vital Belikov
Author-email: vital@qwe.lv
License: New BSD
Platform: UNKNOWN
Classifier: Development Status :: 4 - Beta
Classifier: Environment :: Web Environment
Classifier: Framework :: Django
Classifier: Intended Audience :: Developers
Classifier: License :: OSI Approved :: BSD License
Classifier: Natural Language :: English
Classifier: Operating System :: Unix
Classifier: Programming Language :: Python :: 2.7
Classifier: Topic :: Utilities
Requires: django(>=1.3)
